bloomfilter3/__init__.py
bloomfilter3/bloom_filter.py
bloomfilter3/cfg.py
bloomfilter3/backends/__init__.py
bloomfilter3/backends/mmap.py
bloomfilter3/hash/__init__.py
bloomfilter3/hash/hashing.py
bloomfilter3-1.0.2.dist-info/METADATA
bloomfilter3-1.0.2.dist-info/WHEEL
bloomfilter3-1.0.2.dist-info/licenses/AUTHORS.md
bloomfilter3-1.0.2.dist-info/licenses/LICENSE.md
bloomfilter3-1.0.2.dist-info/RECORD
