Metadata-Version: 2.1
Name: bloomfilter3
Version: 1.0.2
Summary: A Bloom filter implementation in Python 3
Project-URL: Documentation, https://github.com/AtomicTessellator/bloomfilter3/blob/main/README.md
Project-URL: Issues, https://github.com/AtomicTessellator/bloomfilter3/issues
Project-URL: Source, https://github.com/AtomicTessellator/bloomfilter3
Author-email: Alain Richardt <alain@atomictessellator.com>
License-Expression: MIT
License-File: AUTHORS.md
License-File: LICENSE.md
Classifier: Development Status :: 5 - Production/Stable
Classifier: Programming Language :: Python
Classifier: Programming Language :: Python :: 3.7
Classifier: Programming Language :: Python :: 3.8
Classifier: Programming Language :: Python :: 3.9
Classifier: Programming Language :: Python :: 3.10
Classifier: Programming Language :: Python :: 3.11
Classifier: Programming Language :: Python :: Implementation :: CPython
Classifier: Programming Language :: Python :: Implementation :: PyPy
Requires-Python: >=3.7
